monarch_pylib/__init__.py
monarch_pylib/utils.py
monarch_pylib/decorator/__init__.py
monarch_pylib/decorator/type.py
monarch_pylib/models/__init__.py
monarch_pylib/models/communication.py
monarch_pylib/models/local_computation.py
monarch_pylib/models/transmission.py
monarch_pylib/models/v2v_computation.py
monarch_pylib/type/transmission_type.py
monarch_pylib-0.5.7.dist-info/METADATA
monarch_pylib-0.5.7.dist-info/WHEEL
monarch_pylib-0.5.7.dist-info/top_level.txt
monarch_pylib-0.5.7.dist-info/RECORD
