Metadata-Version: 2.4
Name: monarch-pylib
Version: 0.5.7
Summary: Monarch Python Library
Author-email: Ali36Saadat <Ali36Saadat@gmail.com>
License: MIT
Project-URL: Homepage, https://github.com/ali36saadat/monarch-pylib
Project-URL: Source, https://github.com/ali36saadat/monarch-pylib
Project-URL: Tracker, https://github.com/ali36saadat/monarch-pylib/issues
Classifier: Development Status :: 3 - Alpha
Classifier: Intended Audience :: Developers
Classifier: License :: OSI Approved :: MIT License
Classifier: Programming Language :: Python :: 3
Classifier: Programming Language :: Python :: 3 :: Only
Classifier: Programming Language :: Python :: 3.10
Classifier: Programming Language :: Python :: 3.11
Classifier: Programming Language :: Python :: 3.12
Classifier: Programming Language :: Python :: 3.13
Classifier: Programming Language :: Python :: 3.14
Requires-Python: >=3.10
